[
  {
    "address": "mzgWcLZecvcx35dinGFDk2AKkCU83z2J2A",
    "input-txid": "7ae7c5dfa4ae715641f3f33f600b768af27d163c38e8b8b9df3821c49e163d0b",
    "time": "1660501231",
    "amount": "10000000",
    "status": "immature",
    "age-in-day": "0",
    "coin-day-weight": "0",
    "proof-of-stake-difficulty": 21.61444591029024,
    "minting-probability-10min": 0,
    "minting-probability-24h": 0,
    "minting-probability-30d": 0.003771512446156033,
    "minting-probability-90d": 0.03579004958122534,
    "search-interval-in-sec": 0,
    "attempts": 0
  },
  {
    "address": "mzgWcLZecvcx35dinGFDk2AKkCU83z2J2A",
    "input-txid": "1de4e056a488a24e3744f89ab213d430d1482283aba1c09eee07d88e3a079f21",
    "time": "1660499343",
    "amount": "10000000",
    "status": "immature",
    "age-in-day": "0",
    "coin-day-weight": "0",
    "proof-of-stake-difficulty": 21.61444591029024,
    "minting-probability-10min": 0,
    "minting-probability-24h": 0,
    "minting-probability-30d": 0.003771512446156033,
    "minting-probability-90d": 0.03579004958122534,
    "search-interval-in-sec": 0,
    "attempts": 0
  },
  {
    "address": "mzgWcLZecvcx35dinGFDk2AKkCU83z2J2A",
    "input-txid": "00acd3591ff23eb77c4def7193b220623534214c3055f0f3ce3af5db76a96126",
    "time": "1660477482",
    "amount": "10000000",
    "status": "immature",
    "age-in-day": "0",
    "coin-day-weight": "0",
    "proof-of-stake-difficulty": 21.61444591029024,
    "minting-probability-10min": 0,
    "minting-probability-24h": 0,
    "minting-probability-30d": 0.003771512446156033,
    "minting-probability-90d": 0.03579004958122534,
    "search-interval-in-sec": 0,
    "attempts": 0
  },
  {
    "address": "mzgWcLZecvcx35dinGFDk2AKkCU83z2J2A",
    "input-txid": "14514c98bac8cd8f5cd468c6be60a120e737b648971d747855e099afb5bfac29",
    "time": "1660501223",
    "amount": "10000000",
    "status": "immature",
    "age-in-day": "0",
    "coin-day-weight": "0",
    "proof-of-stake-difficulty": 21.61444591029024,
    "minting-probability-10min": 0,
    "minting-probability-24h": 0,
    "minting-probability-30d": 0.003771512446156033,
    "minting-probability-90d": 0.03579004958122534,
    "search-interval-in-sec": 0,
    "attempts": 0
  },
  {
    "address": "mzgWcLZecvcx35dinGFDk2AKkCU83z2J2A",
    "input-txid": "ce723371343c7ea6e4ecd5859fe7883d7951878e83af51f45ed9bfec14290932",
    "time": "1660475256",
    "amount": "100000000",
    "status": "immature",
    "age-in-day": "0",
    "coin-day-weight": "0",
    "proof-of-stake-difficulty": 21.61444591029024,
    "minting-probability-10min": 0,
    "minting-probability-24h": 0,
    "minting-probability-30d": 0.03708142634373279,
    "minting-probability-90d": 0.3054298974960703,
    "search-interval-in-sec": 0,
    "attempts": 0
  },
  {
    "address": "mzgWcLZecvcx35dinGFDk2AKkCU83z2J2A",
    "input-txid": "9467bffbb9b5dd1c56d1987cb8be9798fcf88368ecd293691aab105e1c7a6f41",
    "time": "1660475870",
    "amount": "100000000",
    "status": "immature",
    "age-in-day": "0",
    "coin-day-weight": "0",
    "proof-of-stake-difficulty": 21.61444591029024,
    "minting-probability-10min": 0,
    "minting-probability-24h": 0,
    "minting-probability-30d": 0.03708142634373279,
    "minting-probability-90d": 0.3054298974960703,
    "search-interval-in-sec": 0,
    "attempts": 0
  },
  {
    "address": "mkhummTs2MT5GYpTrRYdX8GbbMx6rX3oeR",
    "input-txid": "9467bffbb9b5dd1c56d1987cb8be9798fcf88368ecd293691aab105e1c7a6f41",
    "time": "1660475870",
    "amount": "9949150",
    "status": "immature",
    "age-in-day": "0",
    "coin-day-weight": "0",
    "proof-of-stake-difficulty": 21.61444591029024,
    "minting-probability-10min": 0,
    "minting-probability-24h": 0,
    "minting-probability-30d": 0.003737205833490242,
    "minting-probability-90d": 0.0355692662881324,
    "search-interval-in-sec": 0,
    "attempts": 0
  },
  {
    "address": "mzgWcLZecvcx35dinGFDk2AKkCU83z2J2A",
    "input-txid": "d92ed4f61a8826103847b638a5397ad5e4be04b7dae450470c2d305de72ea349",
    "time": "1660501213",
    "amount": "10000000",
    "status": "immature",
    "age-in-day": "0",
    "coin-day-weight": "0",
    "proof-of-stake-difficulty": 21.61444591029024,
    "minting-probability-10min": 0,
    "minting-probability-24h": 0,
    "minting-probability-30d": 0.003771512446156033,
    "minting-probability-90d": 0.03579004958122534,
    "search-interval-in-sec": 0,
    "attempts": 0
  },
  {
    "address": "mzgWcLZecvcx35dinGFDk2AKkCU83z2J2A",
    "input-txid": "7accd40bf95f2f930258b5f393a2e94427d3022e10b8ecac35c97dca46390f78",
    "time": "1660499372",
    "amount": "10000000",
    "status": "immature",
    "age-in-day": "0",
    "coin-day-weight": "0",
    "proof-of-stake-difficulty": 21.61444591029024,
    "minting-probability-10min": 0,
    "minting-probability-24h": 0,
    "minting-probability-30d": 0.003771512446156033,
    "minting-probability-90d": 0.03579004958122534,
    "search-interval-in-sec": 0,
    "attempts": 0
  },
  {
    "address": "mzgWcLZecvcx35dinGFDk2AKkCU83z2J2A",
    "input-txid": "720ac25c3158d4718b03d7e8842b0db278597ba9420505d84b7828030f107582",
    "time": "1660475149",
    "amount": "100000000",
    "status": "immature",
    "age-in-day": "0",
    "coin-day-weight": "0",
    "proof-of-stake-difficulty": 21.61444591029024,
    "minting-probability-10min": 0,
    "minting-probability-24h": 0,
    "minting-probability-30d": 0.03708142634373279,
    "minting-probability-90d": 0.3054298974960703,
    "search-interval-in-sec": 0,
    "attempts": 0
  },
  {
    "address": "mzgWcLZecvcx35dinGFDk2AKkCU83z2J2A",
    "input-txid": "780592ea3026e30d286f30b80b2a66fc7e6d1dfa0a8f6fa358be611c2cfa3094",
    "time": "1660409389",
    "amount": "45000000000",
    "status": "mature",
    "age-in-day": "1",
    "coin-day-weight": "0",
    "proof-of-stake-difficulty": 21.61444591029024,
    "minting-probability-10min": 0,
    "minting-probability-24h": 0,
    "minting-probability-30d": 0.9999999877598204,
    "minting-probability-90d": 1,
    "search-interval-in-sec": 1,
    "attempts": 31696
  },
  {
    "address": "mzgWcLZecvcx35dinGFDk2AKkCU83z2J2A",
    "input-txid": "172b599e28bac8e7e780457721526898b1719250a63d68683ef5f2c0eec5ce9a",
    "time": "1660501184",
    "amount": "10000000",
    "status": "immature",
    "age-in-day": "0",
    "coin-day-weight": "0",
    "proof-of-stake-difficulty": 21.61444591029024,
    "minting-probability-10min": 0,
    "minting-probability-24h": 0,
    "minting-probability-30d": 0.003771512446156033,
    "minting-probability-90d": 0.03579004958122534,
    "search-interval-in-sec": 0,
    "attempts": 0
  },
  {
    "address": "mzgWcLZecvcx35dinGFDk2AKkCU83z2J2A",
    "input-txid": "f85f82828e21c1e9e22bd68fa2801ab6ceacc270fa947bd9d3973c15fe5964d6",
    "time": "1660501176",
    "amount": "10000000",
    "status": "immature",
    "age-in-day": "0",
    "coin-day-weight": "0",
    "proof-of-stake-difficulty": 21.61444591029024,
    "minting-probability-10min": 0,
    "minting-probability-24h": 0,
    "minting-probability-30d": 0.003771512446156033,
    "minting-probability-90d": 0.03579004958122534,
    "search-interval-in-sec": 0,
    "attempts": 0
  },
  {
    "address": "mzgWcLZecvcx35dinGFDk2AKkCU83z2J2A",
    "input-txid": "8e248b2e04ebfd4a27c8ea21dad715b8917558dde624ee8ca6856b509f3ba4d6",
    "time": "1660187936",
    "amount": "10000000",
    "status": "mature",
    "age-in-day": "3",
    "coin-day-weight": "20",
    "proof-of-stake-difficulty": 21.61444591029024,
    "minting-probability-10min": 1.292639245642491e-07,
    "minting-probability-24h": 1.86138330987573e-05,
    "minting-probability-30d": 0.00459636985450218,
    "minting-probability-90d": 0.03817415552950154,
    "search-interval-in-sec": 1,
    "attempts": 253149
  }
]
